MANIFEST.in
changelog.rst
readme.rst
setup.py
SAValidation.egg-info/PKG-INFO
SAValidation.egg-info/SOURCES.txt
SAValidation.egg-info/dependency_links.txt
SAValidation.egg-info/not-zip-safe
SAValidation.egg-info/requires.txt
SAValidation.egg-info/top_level.txt
savalidation/__init__.py
savalidation/_internal.py
savalidation/helpers.py
savalidation/validators.py
savalidation/version.txt
savalidation/tests/__init__.py
savalidation/tests/examples.py
savalidation/tests/test_examples.py
savalidation/tests/test_refactor.py
savalidation/tests/test_unit.py
savalidation/tests/test_validators.py