Metadata-Version: 1.1
Name: SAValidation
Version: 0.4.1
Summary: Active Record like validation on SQLAlchemy declarative model objects
Home-page: https://github.com/blazelibs/sqlalchemy-validation
Author: Randy Syring
Author-email: randy.syring@level12.io
License: BSD
Platform: UNKNOWN
Classifier: Development Status :: 4 - Beta
Classifier: Intended Audience :: Developers
Classifier: License :: OSI Approved :: BSD License
Classifier: Operating System :: OS Independent
Classifier: Programming Language :: Python :: 2.7
Classifier: Programming Language :: Python :: 3.4
Classifier: Programming Language :: Python :: 3.5
Classifier: Topic :: Database
